ml_algorithms/__init__.py
ml_algorithms/algorithms.py
test/__init__.py
test/test_algorithms.py
metriccoders_ml-0.0.3.dist-info/LICENSE.txt
metriccoders_ml-0.0.3.dist-info/METADATA
metriccoders_ml-0.0.3.dist-info/WHEEL
metriccoders_ml-0.0.3.dist-info/top_level.txt
metriccoders_ml-0.0.3.dist-info/RECORD
