Metadata-Version: 2.1
Name: metriccoders_ml
Version: 0.0.3
Summary: This is a python package to load ML models from Metric Coders repository
Home-page: https://github.com/metriccoders/metriccoders_ml_pypi
Author: Metric Coders Team
Author-email: technologyappsdeveloper@gmail.com
Project-URL: Bug Tracker, https://github.com/metriccoders/metriccoders_ml_pypi/issues
Classifier: Programming Language :: Python :: 3
Classifier: License :: OSI Approved :: MIT License
Classifier: Operating System :: OS Independent
Requires-Python: >=3.6
License-File: LICENSE.txt
